{
  "groups": [
    {
      "name": "application",
      "description": "应用相关信息."
    }
  ],
  "properties": [
    {
      "name": "application.instance-id",
      "type": "java.lang.String",
      "description": "实例ID."
    },
    {
      "name": "application.name",
      "type": "java.lang.String",
      "description": "应用名称."
    },
    {
      "name": "application.module",
      "type": "java.lang.String",
      "description": "模块名称."
    },
    {
      "name": "application.version",
      "type": "java.lang.String",
      "description": "版本号."
    },
    {
      "name": "application.formatted-version",
      "type": "java.lang.String",
      "description": "格式化版本."
    },
    {
      "name": "spring.redis.cache.time",
      "type": "java.lang.Long",
      "description": "缓存时长."
    },
    {
      "name": "spring.redis.cache.time-unit",
      "type": "java.util.concurrent.TimeUnit",
      "description": "缓存时长单位."
    }
  ],
  "hints": []
}
